opa_wasm/__init__.py
opa_wasm/opa_wasm.py
opa_wasm-0.3.2.dist-info/LICENSE
opa_wasm-0.3.2.dist-info/WHEEL
opa_wasm-0.3.2.dist-info/METADATA
opa_wasm-0.3.2.dist-info/RECORD
