Metadata-Version: 2.1
Name: opa-wasm
Version: 0.3.2
Summary: Open Policy Agent WebAssembly SDK for Python
Home-page: https://github.com/a2d24/python-opa-wasm
License: MIT
Keywords: opa,wasm,policy
Author: Imtiaz Mangerah
Author-email: Imtiaz_Mangerah@a2d24.com
Requires-Python: >=3.8,<4.0
Classifier: License :: OSI Approved :: MIT License
Classifier: Programming Language :: Python :: 3
Classifier: Programming Language :: Python :: 3.10
Classifier: Programming Language :: Python :: 3.8
Classifier: Programming Language :: Python :: 3.9
Provides-Extra: cranelift
Provides-Extra: llvm
Requires-Dist: wasmer (>=1.0.0,<2.0.0)
Requires-Dist: wasmer-compiler-cranelift (>=1.0.0,<2.0.0); extra == "cranelift"
Requires-Dist: wasmer-compiler-llvm (>=1.0.0,<2.0.0); extra == "llvm"
Project-URL: Documentation, https://github.com/a2d24/python-opa-wasm
Project-URL: Repository, https://github.com/a2d24/python-opa-wasm
